README.md
pyproject.toml
setup.py
datafns.egg-info/PKG-INFO
datafns.egg-info/SOURCES.txt
datafns.egg-info/dependency_links.txt
datafns.egg-info/top_level.txt
fns/__init__.py
fns/functions.py